deeplex/__init__.py
deeplex/deeplex.py
deeplex-0.0.1.dist-info/LICENSE
deeplex-0.0.1.dist-info/METADATA
deeplex-0.0.1.dist-info/WHEEL
deeplex-0.0.1.dist-info/top_level.txt
deeplex-0.0.1.dist-info/RECORD
