Metadata-Version: 2.1
Name: deeplex
Version: 0.0.1
Summary: Free DeepL translation with Glossaries
Home-page: https://github.com/OrigamiDream/deeplex.git
Author: OrigamiDream
Author-email: hello@origamidream.me
License: MIT
Keywords: machine translation,deepl,free deepl,google translate,free translate,translation,multilingual,mling
Platform: any
Classifier: Development Status :: 4 - Beta
Classifier: Intended Audience :: Developers
Classifier: Environment :: Web Environment
Classifier: License :: OSI Approved :: MIT License
Classifier: Operating System :: OS Independent
Classifier: Programming Language :: Python :: 3.6
Classifier: Programming Language :: Python :: 3.7
Classifier: Programming Language :: Python :: 3.8
Classifier: Programming Language :: Python :: 3.9
Classifier: Programming Language :: Python :: 3.10
Classifier: Topic :: Internet :: WWW/HTTP :: Dynamic Content
Classifier: Topic :: Software Development :: Libraries :: Python Modules
Requires-Python: >=3.6.0
License-File: LICENSE
Requires-Dist: brotli >=1.1.0
Requires-Dist: aiohttp >=3.9.5
